{
  "lastUpdate": "2025-11-04T00:00:00Z",
  "snapshots": [
    {
      "date": "2025-11-04T00:00:00Z",
      "type": "global",
      "professionals": [
        {
          "id": "1",
          "name": "Angie Jones",
          "profilePicture": "https://media.licdn.com/dms/image/v2/C4E03AQGHvMFQ0jDz7w/profile-displayphoto-shrink_800_800/profile-displayphoto-shrink_800_800/0/1589914367714?e=1738195200&v=beta&t=example",
          "linkedinUrl": "https://www.linkedin.com/in/angiejones/",
          "followers": 250000,
          "location": {
            "country": "United States",
            "countryCode": "US"
          },
          "title": "VP of Developer Relations",
          "company": "TBD",
          "lastUpdated": "2025-11-04T00:00:00Z"
        },
        {
          "id": "2",
          "name": "Bas Dijkstra",
          "profilePicture": "https://via.placeholder.com/150",
          "linkedinUrl": "https://www.linkedin.com/in/basdijkstra/",
          "followers": 45000,
          "location": {
            "country": "Netherlands",
            "countryCode": "NL"
          },
          "title": "Test Automation Consultant",
          "company": "Self-employed",
          "lastUpdated": "2025-11-04T00:00:00Z"
        },
        {
          "id": "3",
          "name": "Júlio de Lima",
          "profilePicture": "https://via.placeholder.com/150",
          "linkedinUrl": "https://www.linkedin.com/in/juliodelimaqa/",
          "followers": 38000,
          "location": {
            "country": "Brazil",
            "countryCode": "BR",
            "state": "São Paulo",
            "stateCode": "SP"
          },
          "title": "QA Consultant",
          "company": "Iterasys",
          "lastUpdated": "2025-11-04T00:00:00Z"
        },
        {
          "id": "4",
          "name": "Nikolay Advolodkin",
          "profilePicture": "https://via.placeholder.com/150",
          "linkedinUrl": "https://www.linkedin.com/in/nikolayadvolodkin/",
          "followers": 35000,
          "location": {
            "country": "United States",
            "countryCode": "US"
          },
          "title": "Founder & CEO",
          "company": "Ultimate QA",
          "lastUpdated": "2025-11-04T00:00:00Z"
        },
        {
          "id": "5",
          "name": "Joe Colantonio",
          "profilePicture": "https://via.placeholder.com/150",
          "linkedinUrl": "https://www.linkedin.com/in/joecolantonio/",
          "followers": 32000,
          "location": {
            "country": "United States",
            "countryCode": "US"
          },
          "title": "Test Automation & Performance Testing Expert",
          "company": "Test Guild",
          "lastUpdated": "2025-11-04T00:00:00Z"
        },
        {
          "id": "6",
          "name": "Elias Nogueira",
          "profilePicture": "https://via.placeholder.com/150",
          "linkedinUrl": "https://www.linkedin.com/in/eliasnogueira/",
          "followers": 28000,
          "location": {
            "country": "Brazil",
            "countryCode": "BR",
            "state": "São Paulo",
            "stateCode": "SP"
          },
          "title": "Senior Software Engineer in Test",
          "company": "Backbase",
          "lastUpdated": "2025-11-04T00:00:00Z"
        },
        {
          "id": "7",
          "name": "Maaret Pyhäjärvi",
          "profilePicture": "https://via.placeholder.com/150",
          "linkedinUrl": "https://www.linkedin.com/in/maaret/",
          "followers": 26000,
          "location": {
            "country": "Finland",
            "countryCode": "FI"
          },
          "title": "Principal Test Engineer",
          "company": "Vaisala",
          "lastUpdated": "2025-11-04T00:00:00Z"
        },
        {
          "id": "8",
          "name": "Alan Richardson",
          "profilePicture": "https://via.placeholder.com/150",
          "linkedinUrl": "https://www.linkedin.com/in/eviltester/",
          "followers": 24000,
          "location": {
            "country": "United Kingdom",
            "countryCode": "GB"
          },
          "title": "Software Testing Consultant",
          "company": "Evil Tester",
          "lastUpdated": "2025-11-04T00:00:00Z"
        },
        {
          "id": "9",
          "name": "Kristin Jackvony",
          "profilePicture": "https://via.placeholder.com/150",
          "linkedinUrl": "https://www.linkedin.com/in/kristinjackvony/",
          "followers": 22000,
          "location": {
            "country": "United States",
            "countryCode": "US"
          },
          "title": "QA Manager",
          "company": "Netflix",
          "lastUpdated": "2025-11-04T00:00:00Z"
        },
        {
          "id": "10",
          "name": "Paul Grizzaffi",
          "profilePicture": "https://via.placeholder.com/150",
          "linkedinUrl": "https://www.linkedin.com/in/pgrizzaffi/",
          "followers": 20000,
          "location": {
            "country": "United States",
            "countryCode": "US"
          },
          "title": "Lead QA Automation Engineer",
          "company": "Sauce Labs",
          "lastUpdated": "2025-11-04T00:00:00Z"
        }
      ],
      "totalCount": 10
    },
    {
      "date": "2025-10-15T00:00:00Z",
      "type": "global",
      "professionals": [
        {
          "id": "1",
          "name": "Angie Jones",
          "profilePicture": "https://via.placeholder.com/150",
          "linkedinUrl": "https://www.linkedin.com/in/angiejones/",
          "followers": 248000,
          "location": {
            "country": "United States",
            "countryCode": "US"
          },
          "title": "VP of Developer Relations",
          "lastUpdated": "2025-10-15T00:00:00Z"
        },
        {
          "id": "3",
          "name": "Júlio de Lima",
          "profilePicture": "https://via.placeholder.com/150",
          "linkedinUrl": "https://www.linkedin.com/in/juliodelimaqa/",
          "followers": 44000,
          "location": {
            "country": "Brazil",
            "countryCode": "BR"
          },
          "lastUpdated": "2025-10-15T00:00:00Z"
        },
        {
          "id": "2",
          "name": "Bas Dijkstra",
          "profilePicture": "https://via.placeholder.com/150",
          "linkedinUrl": "https://www.linkedin.com/in/basdijkstra/",
          "followers": 43000,
          "location": {
            "country": "Netherlands",
            "countryCode": "NL"
          },
          "lastUpdated": "2025-10-15T00:00:00Z"
        },
        {
          "id": "4",
          "name": "Nikolay Advolodkin",
          "profilePicture": "https://via.placeholder.com/150",
          "linkedinUrl": "https://www.linkedin.com/in/nikolayadvolodkin/",
          "followers": 34500,
          "location": {
            "country": "United States",
            "countryCode": "US"
          },
          "lastUpdated": "2025-10-15T00:00:00Z"
        },
        {
          "id": "5",
          "name": "Joe Colantonio",
          "profilePicture": "https://via.placeholder.com/150",
          "linkedinUrl": "https://www.linkedin.com/in/joecolantonio/",
          "followers": 31500,
          "location": {
            "country": "United States",
            "countryCode": "US"
          },
          "lastUpdated": "2025-10-15T00:00:00Z"
        },
        {
          "id": "6",
          "name": "Elias Nogueira",
          "profilePicture": "https://via.placeholder.com/150",
          "linkedinUrl": "https://www.linkedin.com/in/eliasnogueira/",
          "followers": 27500,
          "location": {
            "country": "Brazil",
            "countryCode": "BR"
          },
          "lastUpdated": "2025-10-15T00:00:00Z"
        },
        {
          "id": "7",
          "name": "Maaret Pyhäjärvi",
          "profilePicture": "https://via.placeholder.com/150",
          "linkedinUrl": "https://www.linkedin.com/in/maaret/",
          "followers": 25800,
          "location": {
            "country": "Finland",
            "countryCode": "FI"
          },
          "lastUpdated": "2025-10-15T00:00:00Z"
        },
        {
          "id": "8",
          "name": "Alan Richardson",
          "profilePicture": "https://via.placeholder.com/150",
          "linkedinUrl": "https://www.linkedin.com/in/eviltester/",
          "followers": 23800,
          "location": {
            "country": "United Kingdom",
            "countryCode": "GB"
          },
          "lastUpdated": "2025-10-15T00:00:00Z"
        },
        {
          "id": "9",
          "name": "Kristin Jackvony",
          "profilePicture": "https://via.placeholder.com/150",
          "linkedinUrl": "https://www.linkedin.com/in/kristinjackvony/",
          "followers": 21800,
          "location": {
            "country": "United States",
            "countryCode": "US"
          },
          "lastUpdated": "2025-10-15T00:00:00Z"
        },
        {
          "id": "10",
          "name": "Paul Grizzaffi",
          "profilePicture": "https://via.placeholder.com/150",
          "linkedinUrl": "https://www.linkedin.com/in/pgrizzaffi/",
          "followers": 19800,
          "location": {
            "country": "United States",
            "countryCode": "US"
          },
          "lastUpdated": "2025-10-15T00:00:00Z"
        }
      ],
      "totalCount": 10
    }
  ]
}
